patronous/__init__.py
patronous/cli.py
patronous/utils.py
patronous-0.6.dist-info/DESCRIPTION.rst
patronous-0.6.dist-info/METADATA
patronous-0.6.dist-info/RECORD
patronous-0.6.dist-info/WHEEL
patronous-0.6.dist-info/entry_points.txt
patronous-0.6.dist-info/metadata.json
patronous-0.6.dist-info/top_level.txt
