Metadata-Version: 2.0
Name: patronous
Version: 0.6
Summary: aws lambda function deployer
Home-page: http://github.com/zkrhm/patronous
Author: zkrhm
Author-email: UNKNOWN
License: MIT
Platform: UNKNOWN
